setup.py
minc/__init__.py
minc.egg-info/PKG-INFO
minc.egg-info/SOURCES.txt
minc.egg-info/dependency_links.txt
minc.egg-info/not-zip-safe
minc.egg-info/top_level.txt