Metadata-Version: 1.1
Name: minc
Version: 0.0.0
Summary: MIscreaNt Cryptotool
Home-page: https://github.com/miscreant/minclib
Author: Tony Arcieri
Author-email: bascule@gmail.com
License: MIT license
Keywords: cryptography,security,signatures
Platform: UNKNOWN
Classifier: Development Status :: 2 - Pre-Alpha
Classifier: Intended Audience :: Developers
Classifier: License :: OSI Approved :: MIT License
Classifier: Natural Language :: English
